README.md
setup.py
hotstepper/__init__.py
hotstepper.egg-info/PKG-INFO
hotstepper.egg-info/SOURCES.txt
hotstepper.egg-info/dependency_links.txt
hotstepper.egg-info/requires.txt
hotstepper.egg-info/top_level.txt
hotstepper/analysis/Sequency.py
hotstepper/analysis/__init__.py
hotstepper/analysis/statistics.py
hotstepper/basis/Bases.py
hotstepper/basis/Basis.py
hotstepper/basis/__init__.py
hotstepper/core/AbstractSteps.py
hotstepper/core/Step.py
hotstepper/core/Steps.py
hotstepper/core/__init__.py
hotstepper/core/data_model.py
hotstepper/mixins/FilterFunctionsMixin.py
hotstepper/mixins/MathFunctionsMixin.py
hotstepper/mixins/StepsPlottingMixin.py
hotstepper/mixins/__init__.py
hotstepper/mixins/operations.py
hotstepper/mixins/read_write.py
hotstepper/samples/__init__.py
hotstepper/utilities/__init__.py
hotstepper/utilities/helpers.py