Metadata-Version: 2.1
Name: hotstepper
Version: 1.0.4
Summary: Numpy based step function library.
Home-page: https://github.com/tanglespace/hotstepper
Author: Jackson Storm
Author-email: c6lculus8ntr0py@gmail.com
License: MIT
Project-URL: Documentation, https://hotstepper.readthedocs.io/
Project-URL: Source, https://github.com/tanglespace/hotstepper
Project-URL: Tracker, https://github.com/tanglespace/hotstepper/issues
Platform: UNKNOWN
Classifier: Programming Language :: Python :: 3
Classifier: Operating System :: OS Independent
